LICENSE
README.md
setup.cfg
setup.py
ceres/__init__.py
ceres/builder.py
ceres_graphql.egg-info/PKG-INFO
ceres_graphql.egg-info/SOURCES.txt
ceres_graphql.egg-info/dependency_links.txt
ceres_graphql.egg-info/requires.txt
ceres_graphql.egg-info/top_level.txt